#include <ctype.h>
#include <stdio.h>
#include <stddef.h>

#include "lua.h"
#include "lualib.h"
#include "lauxlib.h"
#include "ldebug.h"
#include "lobject.h"
#include "lopcodes.h"


#define luac_c
#define LUA_CORE

#define VOID(p)		((const void*)(p))
#define toproto(L,i) getproto(L->top+(i))


/* ORDER OP */

LUAI_DDEF const char *const luaP_opnames[NUM_OPCODES+1] = {
  "MOVE",
  "LOADK",
  "LOADKX",
  "LOADBOOL",
  "LOADNIL",
  "GETUPVAL",
  "GETTABUP",
  "GETTABLE",
  "SETTABUP",
  "SETUPVAL",
  "SETTABLE",
  "NEWTABLE",
  "SELF",
  "ADD",
  "SUB",
  "MUL",
  "MOD",
  "POW",
  "DIV",
  "IDIV",
  "BAND",
  "BOR",
  "BXOR",
  "SHL",
  "SHR",
  "UNM",
  "BNOT",
  "NOT",
  "LEN",
  "CONCAT",
  "JMP",
  "EQ",
  "LT",
  "LE",
  "TEST",
  "TESTSET",
  "CALL",
  "TAILCALL",
  "RETURN",
  "FORLOOP",
  "FORPREP",
  "TFORCALL",
  "TFORLOOP",
  "SETLIST",
  "CLOSURE",
  "VARARG",
  "EXTRAARG",
  NULL
};


#define opmode(t,a,b,c,m) (((t)<<7) | ((a)<<6) | ((b)<<4) | ((c)<<2) | (m))

const lu_byte luaP_opmodes[NUM_OPCODES] = {
/*       T  A    B       C     mode		   opcode	*/
  opmode(0, 1, OpArgR, OpArgN, iABC)		/* OP_MOVE */
 ,opmode(0, 1, OpArgK, OpArgN, iABx)		/* OP_LOADK */
 ,opmode(0, 1, OpArgN, OpArgN, iABx)		/* OP_LOADKX */
 ,opmode(0, 1, OpArgU, OpArgU, iABC)		/* OP_LOADBOOL */
 ,opmode(0, 1, OpArgU, OpArgN, iABC)		/* OP_LOADNIL */
 ,opmode(0, 1, OpArgU, OpArgN, iABC)		/* OP_GETUPVAL */
 ,opmode(0, 1, OpArgU, OpArgK, iABC)		/* OP_GETTABUP */
 ,opmode(0, 1, OpArgR, OpArgK, iABC)		/* OP_GETTABLE */
 ,opmode(0, 0, OpArgK, OpArgK, iABC)		/* OP_SETTABUP */
 ,opmode(0, 0, OpArgU, OpArgN, iABC)		/* OP_SETUPVAL */
 ,opmode(0, 0, OpArgK, OpArgK, iABC)		/* OP_SETTABLE */
 ,opmode(0, 1, OpArgU, OpArgU, iABC)		/* OP_NEWTABLE */
 ,opmode(0, 1, OpArgR, OpArgK, iABC)		/* OP_SELF */
 ,opmode(0, 1, OpArgK, OpArgK, iABC)		/* OP_ADD */
 ,opmode(0, 1, OpArgK, OpArgK, iABC)		/* OP_SUB */
 ,opmode(0, 1, OpArgK, OpArgK, iABC)		/* OP_MUL */
 ,opmode(0, 1, OpArgK, OpArgK, iABC)		/* OP_MOD */
 ,opmode(0, 1, OpArgK, OpArgK, iABC)		/* OP_POW */
 ,opmode(0, 1, OpArgK, OpArgK, iABC)		/* OP_DIV */
 ,opmode(0, 1, OpArgK, OpArgK, iABC)		/* OP_IDIV */
 ,opmode(0, 1, OpArgK, OpArgK, iABC)		/* OP_BAND */
 ,opmode(0, 1, OpArgK, OpArgK, iABC)		/* OP_BOR */
 ,opmode(0, 1, OpArgK, OpArgK, iABC)		/* OP_BXOR */
 ,opmode(0, 1, OpArgK, OpArgK, iABC)		/* OP_SHL */
 ,opmode(0, 1, OpArgK, OpArgK, iABC)		/* OP_SHR */
 ,opmode(0, 1, OpArgR, OpArgN, iABC)		/* OP_UNM */
 ,opmode(0, 1, OpArgR, OpArgN, iABC)		/* OP_BNOT */
 ,opmode(0, 1, OpArgR, OpArgN, iABC)		/* OP_NOT */
 ,opmode(0, 1, OpArgR, OpArgN, iABC)		/* OP_LEN */
 ,opmode(0, 1, OpArgR, OpArgR, iABC)		/* OP_CONCAT */
 ,opmode(0, 0, OpArgR, OpArgN, iAsBx)		/* OP_JMP */
 ,opmode(1, 0, OpArgK, OpArgK, iABC)		/* OP_EQ */
 ,opmode(1, 0, OpArgK, OpArgK, iABC)		/* OP_LT */
 ,opmode(1, 0, OpArgK, OpArgK, iABC)		/* OP_LE */
 ,opmode(1, 0, OpArgN, OpArgU, iABC)		/* OP_TEST */
 ,opmode(1, 1, OpArgR, OpArgU, iABC)		/* OP_TESTSET */
 ,opmode(0, 1, OpArgU, OpArgU, iABC)		/* OP_CALL */
 ,opmode(0, 1, OpArgU, OpArgU, iABC)		/* OP_TAILCALL */
 ,opmode(0, 0, OpArgU, OpArgN, iABC)		/* OP_RETURN */
 ,opmode(0, 1, OpArgR, OpArgN, iAsBx)		/* OP_FORLOOP */
 ,opmode(0, 1, OpArgR, OpArgN, iAsBx)		/* OP_FORPREP */
 ,opmode(0, 0, OpArgN, OpArgU, iABC)		/* OP_TFORCALL */
 ,opmode(0, 1, OpArgR, OpArgN, iAsBx)		/* OP_TFORLOOP */
 ,opmode(0, 0, OpArgU, OpArgU, iABC)		/* OP_SETLIST */
 ,opmode(0, 1, OpArgU, OpArgN, iABx)		/* OP_CLOSURE */
 ,opmode(0, 1, OpArgU, OpArgN, iABC)		/* OP_VARARG */
 ,opmode(0, 0, OpArgU, OpArgU, iAx)		/* OP_EXTRAARG */
};

static void PrintString(const TString* ts)
{
 const char* s=getstr(ts);
 size_t i,n=tsslen(ts);
 printf("%c",'"');
 for (i=0; i<n; i++)
 {
  int c=(int)(unsigned char)s[i];
  switch (c)
  {
   case '"':  printf("\\\""); break;
   case '\\': printf("\\\\"); break;
   case '\a': printf("\\a"); break;
   case '\b': printf("\\b"); break;
   case '\f': printf("\\f"); break;
   case '\n': printf("\\n"); break;
   case '\r': printf("\\r"); break;
   case '\t': printf("\\t"); break;
   case '\v': printf("\\v"); break;
   default:	if (isprint(c))
   			printf("%c",c);
		else
			printf("\\%03d",c);
  }
 }
 printf("%c",'"');
}

static void PrintConstant(const Proto* f, int i)
{
 const TValue* o=&f->k[i];
 switch (ttype(o))
 {
  case LUA_TNIL:
	printf("nil");
	break;
  case LUA_TBOOLEAN:
	printf(bvalue(o) ? "true" : "false");
	break;
  case LUA_TNUMFLT:
	{
	char buff[100];
	sprintf(buff,LUA_NUMBER_FMT,fltvalue(o));
	printf("%s",buff);
	if (buff[strspn(buff,"-0123456789")]=='\0') printf(".0");
	break;
	}
  case LUA_TNUMINT:
	printf(LUA_INTEGER_FMT,ivalue(o));
	break;
  case LUA_TSHRSTR: case LUA_TLNGSTR:
	PrintString(tsvalue(o));
	break;
  default:				/* cannot happen */
	printf("? type=%d",ttype(o));
	break;
 }
}

#define UPVALNAME(x) ((f->upvalues[x].name) ? getstr(f->upvalues[x].name) : "-")
#define MYK(x)		(-1-(x))

static void PrintCode(const Proto* f)
{
 const Instruction* code=f->code;
 int pc,n=f->sizecode;
 for (pc=0; pc<n; pc++)
 {
  Instruction i=code[pc];
  OpCode o=GET_OPCODE(i);
  int a=GETARG_A(i);
  int b=GETARG_B(i);
  int c=GETARG_C(i);
  int ax=GETARG_Ax(i);
  int bx=GETARG_Bx(i);
  int sbx=GETARG_sBx(i);
  int line=getfuncline(f,pc);
  printf("\t%d\t",pc+1);
  if (line>0) printf("[%d]\t",line); else printf("[-]\t");
  printf("%-9s\t",luaP_opnames[o]);
  switch (getOpMode(o))
  {
   case iABC:
    printf("%d",a);
    if (getBMode(o)!=OpArgN) printf(" %d",ISK(b) ? (MYK(INDEXK(b))) : b);
    if (getCMode(o)!=OpArgN) printf(" %d",ISK(c) ? (MYK(INDEXK(c))) : c);
    break;
   case iABx:
    printf("%d",a);
    if (getBMode(o)==OpArgK) printf(" %d",MYK(bx));
    if (getBMode(o)==OpArgU) printf(" %d",bx);
    break;
   case iAsBx:
    printf("%d %d",a,sbx);
    break;
   case iAx:
    printf("%d",MYK(ax));
    break;
  }
  switch (o)
  {
   case OP_LOADK:
    printf("\t; "); PrintConstant(f,bx);
    break;
   case OP_GETUPVAL:
   case OP_SETUPVAL:
    printf("\t; %s",UPVALNAME(b));
    break;
   case OP_GETTABUP:
    printf("\t; %s",UPVALNAME(b));
    if (ISK(c)) { printf(" "); PrintConstant(f,INDEXK(c)); }
    break;
   case OP_SETTABUP:
    printf("\t; %s",UPVALNAME(a));
    if (ISK(b)) { printf(" "); PrintConstant(f,INDEXK(b)); }
    if (ISK(c)) { printf(" "); PrintConstant(f,INDEXK(c)); }
    break;
   case OP_GETTABLE:
   case OP_SELF:
    if (ISK(c)) { printf("\t; "); PrintConstant(f,INDEXK(c)); }
    break;
   case OP_SETTABLE:
   case OP_ADD:
   case OP_SUB:
   case OP_MUL:
   case OP_MOD:
   case OP_POW:
   case OP_DIV:
   case OP_IDIV:
   case OP_BAND:
   case OP_BOR:
   case OP_BXOR:
   case OP_SHL:
   case OP_SHR:
   case OP_EQ:
   case OP_LT:
   case OP_LE:
    if (ISK(b) || ISK(c))
    {
     printf("\t; ");
     if (ISK(b)) PrintConstant(f,INDEXK(b)); else printf("-");
     printf(" ");
     if (ISK(c)) PrintConstant(f,INDEXK(c)); else printf("-");
    }
    break;
   case OP_JMP:
   case OP_FORLOOP:
   case OP_FORPREP:
   case OP_TFORLOOP:
    printf("\t; to %d",sbx+pc+2);
    break;
   case OP_CLOSURE:
    printf("\t; %p",VOID(f->p[bx]));
    break;
   case OP_SETLIST:
    if (c==0) printf("\t; %d",(int)code[++pc]); else printf("\t; %d",c);
    break;
   case OP_EXTRAARG:
    printf("\t; "); PrintConstant(f,ax);
    break;
   default:
    break;
  }
  printf("\n");
 }
}

#define SS(x)	((x==1)?"":"s")
#define S(x)	(int)(x),SS(x)

static void PrintHeader(const Proto* f)
{
 const char* s=f->source ? getstr(f->source) : "=?";
 if (*s=='@' || *s=='=')
  s++;
 else if (*s==LUA_SIGNATURE[0])
  s="(bstring)";
 else
  s="(string)";
 printf("\n%s <%s:%d,%d> (%d instruction%s at %p)\n",
 	(f->linedefined==0)?"main":"function",s,
	f->linedefined,f->lastlinedefined,
	S(f->sizecode),VOID(f));
 printf("%d%s param%s, %d slot%s, %d upvalue%s, ",
	(int)(f->numparams),f->is_vararg?"+":"",SS(f->numparams),
	S(f->maxstacksize),S(f->sizeupvalues));
 printf("%d local%s, %d constant%s, %d function%s\n",
	S(f->sizelocvars),S(f->sizek),S(f->sizep));
}

static void PrintDebug(const Proto* f)
{
 int i,n;
 n=f->sizek;
 printf("constants (%d) for %p:\n",n,VOID(f));
 for (i=0; i<n; i++)
 {
  printf("\t%d\t",i+1);
  PrintConstant(f,i);
  printf("\n");
 }
 n=f->sizelocvars;
 printf("locals (%d) for %p:\n",n,VOID(f));
 for (i=0; i<n; i++)
 {
  printf("\t%d\t%s\t%d\t%d\n",
  i,getstr(f->locvars[i].varname),f->locvars[i].startpc+1,f->locvars[i].endpc+1);
 }
 n=f->sizeupvalues;
 printf("upvalues (%d) for %p:\n",n,VOID(f));
 for (i=0; i<n; i++)
 {
  printf("\t%d\t%s\t%d\t%d\n",
  i,UPVALNAME(i),f->upvalues[i].instack,f->upvalues[i].idx);
 }
}

static void PrintFunction(const Proto* f, int full)
{
 int i,n=f->sizep;
 PrintHeader(f);
 PrintCode(f);
 if (full) PrintDebug(f);
 for (i=0; i<n; i++) PrintFunction(f->p[i],full);
}

static int dis_dis(lua_State *L)
{
  int n = lua_gettop(L);
  if (n != 1)
  {
    lua_pushliteral(L, "incorrect argument");
    lua_error(L);
  }

  if (!lua_isfunction(L, 1))
  {
    lua_pushliteral(L, "incorrect argument");
    lua_error(L);
  }

  Proto* f = toproto(L, -1);
  PrintFunction(f, 0);
  return 0;
}

static int dis_full(lua_State *L)
{
  int n = lua_gettop(L);
  if (n != 1)
  {
    lua_pushliteral(L, "incorrect argument");
    lua_error(L);
  }

  if (!lua_isfunction(L, 1))
  {
    lua_pushliteral(L, "incorrect argument");
    lua_error(L);
  }

  Proto* f = toproto(L, -1);
  PrintFunction(f, 1);
  return 0;
}

/*
** functions for 'dis' library
*/
static const luaL_Reg dislib[] = {
  {"dis", dis_dis},
  {"disfull", dis_full},
  {NULL, NULL}
};


LUAMOD_API int luaopen_dis (lua_State *L)
{
  luaL_newlib(L, dislib);  /* new module */
  return 1;
}